brain_boost/__init__.py
brain_boost/general_knowledge.py
brain_boost/logic_exercise.py
brain_boost/memory_exercise.py
brain_boost/mental_math.py
brain_boost/performance_analysis.py
brain_boost/progress_tracker.py
brain_boost-0.2.1.dist-info/METADATA
brain_boost-0.2.1.dist-info/WHEEL
brain_boost-0.2.1.dist-info/top_level.txt
brain_boost-0.2.1.dist-info/RECORD
